csrf_sentry/__init__.py
csrf_sentry/main.py
csrf_sentry/prompts.py
csrf_sentry-2025.12.21200926.dist-info/METADATA
csrf_sentry-2025.12.21200926.dist-info/WHEEL
csrf_sentry-2025.12.21200926.dist-info/top_level.txt
csrf_sentry-2025.12.21200926.dist-info/RECORD
