Metadata-Version: 2.4
Name: csrf-sentry
Version: 2025.12.21200926
Summary: Helps developers implement tailored CSRF protection strategies without tokens, ensuring robust security and easy integration.
Author-email: csrf-sentry <hi@eugene.plus>
License: MIT
Project-URL: Homepage, https://github.com/chigwell/csrf-sentry
Requires-Python: >=3.9
Requires-Dist: langchain-llm7>=0.0.0
Requires-Dist: llmatch-messages>=0.0.0
Requires-Dist: langchain-core>=0.3.0
